{
    "gt_parse": {
        "menu": [
            {
                "nm": "J.STB PROMO",
                "price": "17500"
            },
            {
                "nm": "Y.B.BAT",
                "price": "46000"
            },
            {
                "nm": "Y.BASO PROM",
                "price": "27500"
            }
        ],
        "total": {
            "total_price": "91000",
            "cashprice": "91000"
        }
    },
    "meta": {
        "version": "2.0.0",
        "split": "test",
        "image_id": 1,
        "image_size": {
            "width": 960,
            "height": 1280
        }
    },
    "valid_line": [
        {
            "words": [
                {
                    "quad": {
                        "x2": 280,
                        "y3": 711,
                        "x3": 280,
                        "y4": 711,
                        "x1": 131,
                        "y1": 672,
                        "x4": 131,
                        "y2": 672
                    },
                    "is_key": 0,
                    "row_id": 5872,
                    "text": "J.STB"
                },
                {
                    "quad": {
                        "x2": 451,
                        "y3": 709,
                        "x3": 451,
                        "y4": 709,
                        "x1": 312,
                        "y1": 672,
                        "x4": 312,
                        "y2": 672
                    },
                    "is_key": 0,
                    "row_id": 5872,
                    "text": "PROMO"
                }
            ],
            "category": "menu.nm",
            "group_id": 3,
            "sub_group_id": 0
        },
        {
            "words": [
                {
                    "quad": {
                        "x2": 824,
                        "y3": 712,
                        "x3": 824,
                        "y4": 712,
                        "x1": 685,
                        "y1": 675,
                        "x4": 685,
                        "y2": 675
                    },
                    "is_key": 0,
                    "row_id": 5872,
                    "text": "17500"
                }
            ],
            "category": "menu.price",
            "group_id": 3,
            "sub_group_id": 0
        },
        {
            "words": [
                {
                    "quad": {
                        "x2": 335,
                        "y3": 762,
                        "x3": 335,
                        "y4": 766,
                        "x1": 128,
                        "y1": 723,
                        "x4": 129,
                        "y2": 723
                    },
                    "is_key": 0,
                    "row_id": 5873,
                    "text": "Y.B.BAT"
                }
            ],
            "category": "menu.nm",
            "group_id": 4,
            "sub_group_id": 0
        },
        {
            "words": [
                {
                    "quad": {
                        "x2": 824,
                        "y3": 764,
                        "x3": 824,
                        "y4": 764,
                        "x1": 680,
                        "y1": 726,
                        "x4": 680,
                        "y2": 726
                    },
                    "is_key": 0,
                    "row_id": 5873,
                    "text": "46000"
                }
            ],
            "category": "menu.price",
            "group_id": 4,
            "sub_group_id": 0
        },
        {
            "words": [
                {
                    "quad": {
                        "x2": 308,
                        "y3": 818,
                        "x3": 308,
                        "y4": 818,
                        "x1": 125,
                        "y1": 776,
                        "x4": 125,
                        "y2": 776
                    },
                    "is_key": 0,
                    "row_id": 5874,
                    "text": "Y.BASO"
                },
                {
                    "quad": {
                        "x2": 450,
                        "y3": 813,
                        "x3": 450,
                        "y4": 813,
                        "x1": 342,
                        "y1": 773,
                        "x4": 342,
                        "y2": 773
                    },
                    "is_key": 0,
                    "row_id": 5874,
                    "text": "PROM"
                }
            ],
            "category": "menu.nm",
            "group_id": 5,
            "sub_group_id": 0
        },
        {
            "words": [
                {
                    "quad": {
                        "x2": 824,
                        "y3": 815,
                        "x3": 824,
                        "y4": 815,
                        "x1": 682,
                        "y1": 776,
                        "x4": 682,
                        "y2": 776
                    },
                    "is_key": 0,
                    "row_id": 5874,
                    "text": "27500"
                }
            ],
            "category": "menu.price",
            "group_id": 5,
            "sub_group_id": 0
        },
        {
            "words": [
                {
                    "quad": {
                        "x2": 409,
                        "y3": 874,
                        "x3": 409,
                        "y4": 874,
                        "x1": 130,
                        "y1": 825,
                        "x4": 130,
                        "y2": 825
                    },
                    "is_key": 1,
                    "row_id": 5875,
                    "text": "TOTAL"
                },
                {
                    "quad": {
                        "x2": 813,
                        "y3": 867,
                        "x3": 813,
                        "y4": 867,
                        "x1": 539,
                        "y1": 826,
                        "x4": 539,
                        "y2": 826
                    },
                    "is_key": 0,
                    "row_id": 5875,
                    "text": "91000"
                }
            ],
            "category": "total.total_price",
            "group_id": 6,
            "sub_group_id": 0
        },
        {
            "words": [
                {
                    "quad": {
                        "x2": 350,
                        "y3": 931,
                        "x3": 350,
                        "y4": 931,
                        "x1": 127,
                        "y1": 884,
                        "x4": 127,
                        "y2": 884
                    },
                    "is_key": 1,
                    "row_id": 5876,
                    "text": "CASH"
                },
                {
                    "quad": {
                        "x2": 813,
                        "y3": 921,
                        "x3": 813,
                        "y4": 921,
                        "x1": 540,
                        "y1": 880,
                        "x4": 540,
                        "y2": 880
                    },
                    "is_key": 0,
                    "row_id": 5876,
                    "text": "91000"
                }
            ],
            "category": "total.cashprice",
            "group_id": 6,
            "sub_group_id": 0
        }
    ],
    "roi": {
        "x2": 893,
        "y3": 1155,
        "x3": 902,
        "y4": 1202,
        "x1": 80,
        "y1": 136,
        "x4": 103,
        "y2": 177
    },
    "repeating_symbol": [],
    "dontcare": []
}